eeUtil/__init__.py
eeUtil/eeutil.py
eeUtil/gsbucket.py
eeUtil-0.3.0.dist-info/LICENSE
eeUtil-0.3.0.dist-info/METADATA
eeUtil-0.3.0.dist-info/WHEEL
eeUtil-0.3.0.dist-info/top_level.txt
eeUtil-0.3.0.dist-info/RECORD
