Metadata-Version: 2.1
Name: eeUtil
Version: 0.3.0
Summary: Python wrapper for easier data management on Google Earth Engine.
Home-page: https://github.com/fgassert/eeUtil
Author: Francis Gassert
License: MIT
Platform: UNKNOWN
License-File: LICENSE
Requires-Dist: earthengine-api (<0.2,>=0.1.232)
Requires-Dist: google-cloud-storage (<2,>=1.31.1)
Requires-Dist: google-api-core (>=1.22.2<2)
